{
	"$schema": "vscode://schemas/color-theme",
	"name": "Certe Dark (certeroze)",
	"include": "./dark_modern.json",
	"colors": {
		"activityBar.activeBorder": "#FFFFFF",
		"activityBar.background": "#7F3C5B",
		"activityBar.border": "#FFFFFF00",
		"activityBar.foreground": "#FFFFFF",
		"activityBar.inactiveForeground": "#C581A0",
		"activityBarBadge.background": "#B4527F",
		"badge.background": "#7F3C5B",
		"badge.foreground": "#FFFFFF",
		"button.background": "#7F3C5B",
		"button.border": "#7F3C5B",
		"button.hoverBackground": "#7F3C5BE6",
		"editorGutter.modifiedBackground": "#7F3C5B",
		"focusBorder": "#7F3C5B",
		"menu.selectionBackground": "#7F3C5B",
		"panel.background": "#181818",
		"panelTitle.activeBorder": "#7F3C5B",
		"progressBar.background": "#7F3C5B",
		"statusBar.debuggingBackground": "#7F3C5B",
		"statusBar.focusBorder": "#7F3C5B",
		"statusBarItem.focusBorder": "#7F3C5B",
		"statusBarItem.remoteBackground": "#7F3C5B",
		"tab.activeBorderTop": "#7F3C5B",
		"terminalCursor.foreground": "#7F3C5B",
		"terminal.tab.activeBorder": "#7F3C5B",
		"welcomePage.progress.foreground": "#7F3C5B",
		"notebook.selectedCellBackground": "#d3dbcd50",
	},
}
